libchrony/__init.py__
libchrony/chrony_formats.py
libchrony/chrony_socket.py
libchrony/client.py
libchrony/example-methods.py
libchrony/example-reports.py
libchrony/libchrony.py
libchrony/message.py
libchrony-1.0.3.dist-info/METADATA
libchrony-1.0.3.dist-info/WHEEL
libchrony-1.0.3.dist-info/licenses/LICENSE.md
libchrony-1.0.3.dist-info/RECORD
