Metadata-Version: 2.4
Name: libchrony
Version: 1.0.3
Summary: A Python library for monitoring the chrony time synchronization daemon
Project-URL: Homepage, https://gitlab.com/rrobgill/libchrony
Project-URL: Issues, https://gitlab.com/rrobgill/libchrony/issues
Author-email: Rob Gill <rrobgill@protonmail.com>
License-File: LICENSE.md
Classifier: Operating System :: OS Independent
Classifier: Programming Language :: Python :: 3
Requires-Python: >=3.12
